academy_theme/__init__.py
academy_theme/apps.py
academy_theme/context_processors.py
academy_theme/models.py
academy_theme/py.typed
academy_theme/urls.py
academy_theme/views.py
academy_theme/wildewidgets.py
academy_theme/static/academy_theme/css/_globals.scss
academy_theme/static/academy_theme/css/_mixins.scss
academy_theme/static/academy_theme/css/_page.scss
academy_theme/static/academy_theme/css/_ribbon.scss
academy_theme/static/academy_theme/css/theme.css
academy_theme/static/academy_theme/css/theme.css.map
academy_theme/static/academy_theme/css/theme.scss
academy_theme/static/academy_theme/css/boostrap-5.1.3/_breakpoints.scss
academy_theme/static/academy_theme/css/boostrap-5.1.3/_functions.scss
academy_theme/static/academy_theme/css/boostrap-5.1.3/_variables.scss
academy_theme/static/academy_theme/images/android-chrome-192x192.png
academy_theme/static/academy_theme/images/android-chrome-512x512.png
academy_theme/static/academy_theme/images/apple-touch-icon.png
academy_theme/static/academy_theme/images/favicon-16x16.png
academy_theme/static/academy_theme/images/favicon-32x32.png
academy_theme/static/academy_theme/images/favicon.ico
academy_theme/static/academy_theme/images/logo.png
academy_theme/static/academy_theme/images/logo.svg
academy_theme/static/academy_theme/images/site.webmanifest
academy_theme/static/academy_theme/js/theme.js
academy_theme/templates/academy_theme/base--wildewidgets.html
academy_theme/templates/academy_theme/base.html
academy_theme/templates/academy_theme/templatetags/breadcrumb.html
academy_theme/templatetags/__init__.py
academy_theme/templatetags/academy_theme.py
django_theme_academy-0.3.13.dist-info/licenses/LICENSE.txt
django_theme_academy-0.3.13.dist-info/METADATA
django_theme_academy-0.3.13.dist-info/WHEEL
django_theme_academy-0.3.13.dist-info/top_level.txt
django_theme_academy-0.3.13.dist-info/RECORD
