Metadata-Version: 2.4
Name: django-theme-academy
Version: 0.3.13
Summary: A Tabler-based, fixed left sidebar django theme.
Home-page: https://github.com/caltechads/django-theme-academy
Author: Caltech IMSS ADS
Author-email: imss-ads-staff@caltech.edu
Keywords: django
Classifier: Development Status :: 4 - Beta
Classifier: Environment :: Console
Classifier: Intended Audience :: Developers
Classifier: License :: OSI Approved :: BSD License
Classifier: Operating System :: OS Independent
Classifier: Programming Language :: Python
Classifier: Programming Language :: Python :: 3
Classifier: Programming Language :: Python :: 3.7
Classifier: Programming Language :: Python :: 3.8
Classifier: Programming Language :: Python :: 3.9
Classifier: Programming Language :: Python :: 3.10
Classifier: Topic :: Software Development :: Testing
License-File: LICENSE.txt
Requires-Dist: django-wildewidgets>=0.13.49
Dynamic: author
Dynamic: author-email
Dynamic: classifier
Dynamic: description
Dynamic: description-content-type
Dynamic: home-page
Dynamic: keywords
Dynamic: license-file
Dynamic: requires-dist
Dynamic: summary
